aws_slack_notifier_6100/__init__.py
aws_slack_notifier_6100/notifier.py
lambda_slack_notifier-0.2.0.dist-info/LICENSE
lambda_slack_notifier-0.2.0.dist-info/METADATA
lambda_slack_notifier-0.2.0.dist-info/WHEEL
lambda_slack_notifier-0.2.0.dist-info/top_level.txt
lambda_slack_notifier-0.2.0.dist-info/RECORD
